{
  "configuration": {
    "drift_type": "gradual",
    "drift_point": 5000,
    "policy_type": "drift_triggered",
    "error_threshold": null,
    "window_size": 500,
    "budget": 5,
    "retrain_latency": 100,
    "deploy_latency": 5,
    "total_samples": 10000,
    "random_seed": 1213
  },
  "performance_metrics": {
    "overall_accuracy": 0.5289,
    "pre_drift_accuracy": 0.5648,
    "post_drift_accuracy": 0.493,
    "accuracy_drop": -0.07179999999999997
  },
  "retraining_metrics": {
    "total_retrains": 5,
    "budget_used": 5,
    "budget_total": 5,
    "budget_utilization": 1.0,
    "retrains_before_drift": 4,
    "retrains_after_drift": 1,
    "retrain_timestamps": [
      3431,
      3536,
      3641,
      3746,
      5756
    ],
    "retrain_latency_windows": [
      [
        3431,
        3536
      ],
      [
        3536,
        3641
      ],
      [
        3641,
        3746
      ],
      [
        3746,
        3851
      ],
      [
        5756,
        5861
      ]
    ]
  },
  "data_metrics": {
    "predictions_made": 10000,
    "total_samples": 10000
  }
}