{
  "configuration": {
    "drift_type": "recurring",
    "drift_point": 5000,
    "policy_type": "drift_triggered",
    "error_threshold": null,
    "window_size": 500,
    "budget": 20,
    "retrain_latency": 10,
    "deploy_latency": 1,
    "total_samples": 10000,
    "random_seed": 1819
  },
  "performance_metrics": {
    "overall_accuracy": 0.6268,
    "pre_drift_accuracy": 0.6504,
    "post_drift_accuracy": 0.6032,
    "accuracy_drop": -0.04720000000000002
  },
  "retraining_metrics": {
    "total_retrains": 18,
    "budget_used": 18,
    "budget_total": 20,
    "budget_utilization": 0.9,
    "retrains_before_drift": 0,
    "retrains_after_drift": 18,
    "retrain_timestamps": [
      5050,
      5061,
      5094,
      5328,
      5339,
      5350,
      5362,
      5414,
      5425,
      5436,
      5447,
      5458,
      5469,
      5480,
      5491,
      5502,
      5513,
      5524
    ],
    "retrain_latency_windows": [
      [
        5050,
        5061
      ],
      [
        5061,
        5072
      ],
      [
        5094,
        5105
      ],
      [
        5328,
        5339
      ],
      [
        5339,
        5350
      ],
      [
        5350,
        5361
      ],
      [
        5362,
        5373
      ],
      [
        5414,
        5425
      ],
      [
        5425,
        5436
      ],
      [
        5436,
        5447
      ],
      [
        5447,
        5458
      ],
      [
        5458,
        5469
      ],
      [
        5469,
        5480
      ],
      [
        5480,
        5491
      ],
      [
        5491,
        5502
      ],
      [
        5502,
        5513
      ],
      [
        5513,
        5524
      ],
      [
        5524,
        5535
      ]
    ]
  },
  "data_metrics": {
    "predictions_made": 10000,
    "total_samples": 10000
  }
}